ampdup/__init__.py
ampdup/base_client.py
ampdup/connection.py
ampdup/errors.py
ampdup/idle_client.py
ampdup/mpd_client.py
ampdup/parsing.py
ampdup/types.py
ampdup/typing_inspect.py
ampdup/util.py
ampdup-0.12.0.dist-info/LICENSE.md
ampdup-0.12.0.dist-info/WHEEL
ampdup-0.12.0.dist-info/METADATA
ampdup-0.12.0.dist-info/RECORD
