Metadata-Version: 2.1
Name: ampdup
Version: 0.12.0
Summary: A type-hinted async python mpd client library.
Home-page: https://gitlab.com/tarcisioe/ampdup
License: MIT
Keywords: mpd,type,async
Author: Tarcisio Eduardo Moreira Crocomo
Author-email: tarcisio.crocomo+pypi@gmail.com
Requires-Python: >=3.7,<4.0
Classifier: License :: OSI Approved :: MIT License
Classifier: Programming Language :: Python :: 3
Classifier: Programming Language :: Python :: 3.7
Classifier: Programming Language :: Python :: 3.8
Classifier: Programming Language :: Python :: 3.9
Project-URL: Repository, https://gitlab.com/tarcisioe/ampdup
